truchet_tiling/__init__.py
truchet_tiling/themes.py
truchet_tiling/truchet_pattern.py
truchet_tiling/commons/__init__.py
truchet_tiling/commons/constants.py
truchet_tiling/commons/data_classes.py
truchet_tiling/commons/enums.py
truchet_tiling/core/__init__.py
truchet_tiling/core/connector.py
truchet_tiling/core/demo_tile.py
truchet_tiling/core/generators.py
truchet_tiling/core/pattern.py
truchet_tiling/core/quadtree.py
truchet_tiling/core/renderer.py
truchet_tiling/core/stroke.py
truchet_tiling/core/tile.py
truchet_tiling/core/utils.py
truchet_tiling/fills/__init__.py
truchet_tiling/fills/grey.py
truchet_tiling/fills/perlin.py
truchet_tiling/static/truchet_tiles_01/arcs1.svg
truchet_tiling/static/truchet_tiles_01/arcs2.svg
truchet_tiling/static/truchet_tiles_01/arcs4.svg
truchet_tiling/static/truchet_tiles_01/lines1.svg
truchet_tiling/static/truchet_tiles_01/lines2.svg
truchet_tiling/static/truchet_tiles_01/lines4.svg
truchet_tiling-0.0.32.dist-info/METADATA
truchet_tiling-0.0.32.dist-info/WHEEL
truchet_tiling-0.0.32.dist-info/licenses/LICENSE
truchet_tiling-0.0.32.dist-info/RECORD
