Metadata-Version: 2.4
Name: truchet_tiling
Version: 0.0.32
Summary: A truchet tiles generator
Project-URL: Homepage, https://github.com/con-lit/pattern_generator
Project-URL: Issues, https://github.com/con-lit/pattern_generator/issues
Author-email: Constantin Litvak <mail@consta.de>
License-Expression: MIT
License-File: LICENSE
Keywords: generative art,pattern,tiling,truchet
Classifier: License :: OSI Approved :: MIT License
Classifier: Operating System :: OS Independent
Classifier: Programming Language :: Python :: 3
Requires-Python: >=3.8
Requires-Dist: cairosvg
Requires-Dist: numpy
Requires-Dist: perlin-noise
Requires-Dist: pillow
Requires-Dist: pycairo
